{
  "month": 202103,
  "name": "Social Development",
  "sheet_name": "DSD",
  "lead": "Income support to practitioners and to the implementation of Covid compliance measures",
  "paragraph": "Livelihoods from the provision of Early Childhood Development services were severely disrupted by the pandemic, with providers facing challenges with re-opening. There are costs associated with doing so safely, and some parents can no longer afford to pay fees as a result of job losses.",
  "target_lines": [
    5,
    8
  ],
  "achievement_lines": [
    6,
    9
  ],
  "sections": [
    {
      "name": "Programme targets for this department",
      "section_type": "targets",
      "metrics": [
        {
          "name": "Budget",
          "metric_type": "currency",
          "value": -1,
          "dimensions": [],
          "value_target": 588728000,
          "implementation_detail": null
        },
        {
          "name": "Beneficiaries",
          "metric_type": "count",
          "value": 1086,
          "dimensions": [],
          "value_target": 111142,
          "implementation_detail": null
        }
      ],
      "value": null,
      "value_target": null
    },
    {
      "name": "Job opportunities",
      "section_type": "job_opportunities",
      "metrics": [
        {
          "name": "Registration support officers",
          "metric_type": "count",
          "value": 0,
          "dimensions": [],
          "value_target": 500,
          "implementation_detail": null
        }
      ],
      "value": null,
      "value_target": null
    },
    {
      "name": "Jobs retained",
      "section_type": "jobs_retain",
      "metrics": [
        {
          "name": "Retention of social workers",
          "metric_type": "count",
          "value": 1086,
          "dimensions": [
            {
              "name": "Jobs saved by gender",
              "viz": "two_value",
              "lookup": "gender",
              "values": [
                {
                  "key": 1,
                  "value": 0.13
                },
                {
                  "key": 2,
                  "value": 0.87
                }
              ]
            },
            {
              "name": "Jobs saved going to 18-35 year olds",
              "viz": "percentile",
              "lookup": "age",
              "values": [
                {
                  "key": "18-35",
                  "value": 0.61
                }
              ]
            },
            {
              "name": "Jobs saved over time",
              "viz": "line",
              "lookup": "time",
              "values": [
                {
                  "key": "202010",
                  "value": 0
                },
                {
                  "key": "202011",
                  "value": 749
                },
                {
                  "key": "202012",
                  "value": 793
                },
                {
                  "key": "202101",
                  "value": 1086
                }
              ]
            },
            {
              "name": "Jobs saved by province",
              "viz": "bar",
              "lookup": "province",
              "values": [
                {
                  "key": "EC",
                  "value": 282
                },
                {
                  "key": "FS",
                  "value": 0
                },
                {
                  "key": "GP",
                  "value": 305
                },
                {
                  "key": "KZN",
                  "value": 235
                },
                {
                  "key": "LP",
                  "value": 99
                },
                {
                  "key": "MP",
                  "value": 116
                },
                {
                  "key": "NW",
                  "value": 43
                },
                {
                  "key": "NC",
                  "value": 6
                },
                {
                  "key": "WC",
                  "value": 0
                }
              ]
            }
          ],
          "value_target": 74626,
          "implementation_detail": null
        }
      ],
      "value": null,
      "value_target": null
    },
    {
      "name": "Job opportunities",
      "section_type": "job_opportunities",
      "metrics": [
        {
          "name": "ECD income and compliance support",
          "metric_type": "count",
          "value": 0,
          "dimensions": [],
          "value_target": 108833,
          "implementation_detail": null
        }
      ],
      "value": null,
      "value_target": null
    }
  ],
  "implementation_details": []
}
